[
  {
    "ContainingType": "OaisdInterviewBackend.Controllers.NumToTextController",
    "Method": "ConvertToText",
    "RelativePath": "numToText/{input}",
    "HttpMethod": "GET",
    "IsController": true,
    "Order": 0,
    "Parameters": [
      {
        "Name": "input",
        "Type": "System.String",
        "IsRequired": true
      }
    ],
    "ReturnTypes": [
      {
        "Type": "System.Collections.Generic.List\u00601[[OaisdInterviewBackend.Models.ViewModel, OaisdInterviewBackend, Version=1.0.0.0, Culture=neutral, PublicKeyToken=null]]",
        "MediaTypes": [
          "application/json"
        ],
        "StatusCode": 200
      },
      {
        "Type": "Microsoft.AspNetCore.Mvc.ProblemDetails",
        "MediaTypes": [
          "application/json"
        ],
        "StatusCode": 400
      },
      {
        "Type": "System.Void",
        "MediaTypes": [],
        "StatusCode": 500
      }
    ]
  }
]